proxycheck/__init__.py
proxycheck/base.py
proxycheck/exceptions.py
proxycheck/model.py
proxycheck/util.py
proxycheck/awaiting/ip.py
proxycheck/blocking/ip.py
proxycheck/tests/awaiting.py
proxycheck/tests/blocking.py
proxycheck-0.0.4.dist-info/LICENSE
proxycheck-0.0.4.dist-info/METADATA
proxycheck-0.0.4.dist-info/WHEEL
proxycheck-0.0.4.dist-info/top_level.txt
proxycheck-0.0.4.dist-info/RECORD
