Metadata-Version: 2.1
Name: proxycheck
Version: 0.0.4
Summary: Wrapper for Proxycheck
Home-page: https://proxycheck.readthedocs.io/en/latest/
Author: WardPearce
Author-email: wardpearce@protonmail.com
License: GPL-3.0 License
Platform: UNKNOWN
Requires-Python: >=3.6
License-File: LICENSE
Requires-Dist: httpx (>=0.16.1)
Requires-Dist: asynctest
Requires-Dist: sphinxcontrib-trio
Requires-Dist: sphinx-material
